README.rst
setup.cfg
setup.py
Alcathous.egg-info/PKG-INFO
Alcathous.egg-info/SOURCES.txt
Alcathous.egg-info/dependency_links.txt
Alcathous.egg-info/entry_points.txt
Alcathous.egg-info/requires.txt
Alcathous.egg-info/top_level.txt
alcathous/__init__.py
alcathous/datapoint.py
alcathous/datapointmanager.py
alcathous/nodatabehavior.py
alcathous/schema.py
alcathous/worker.py
alcathous/algorithms/__init__.py
alcathous/algorithms/abstractalgorithm.py
alcathous/algorithms/algorithmfactory.py
alcathous/algorithms/average.py
alcathous/algorithms/count.py
alcathous/algorithms/maximum.py
alcathous/algorithms/minimum.py
alcathous/algorithms/weightedaverage.py
tests_unit/__init__.py
tests_unit/test_algorithms.py
tests_unit/test_datapoint.py
tests_unit/test_datapointmanager.py
tests_unit/test_nodatabehavior.py
tests_unit/test_validateconfig.py
tests_unit/test_worker.py
tests_unit/testdatagenerator.py