Metadata-Version: 1.2
Name: Alcathous
Version: 0.3.7
Summary: This software subscribes to mqtt-topics that contain raw sensor data and publishes average values for configurable time spans.
Home-page: https://gitlab.com/pelops/alcathous/
Author: Tobias Gawron-Deutsch
Author-email: tobias@strix.at
License: MIT license
Keywords: mqtt average maximum minimum stream data preparation
Platform: UNKNOWN
Classifier: Development Status :: 4 - Beta
Classifier: Environment :: Console
Classifier: Environment :: No Input/Output (Daemon)
Classifier: Intended Audience :: Developers
Classifier: Programming Language :: Python :: 3
Classifier: Topic :: Utilities
Classifier: Topic :: Home Automation
Classifier: License :: OSI Approved :: MIT License
Requires-Python: >=3.5
